odoo/addons/fieldservice_google_map/README.rst
odoo/addons/fieldservice_google_map/__init__.py
odoo/addons/fieldservice_google_map/__manifest__.py
odoo/addons/fieldservice_google_map/i18n/de.po
odoo/addons/fieldservice_google_map/i18n/es_AR.po
odoo/addons/fieldservice_google_map/i18n/es_CL.po
odoo/addons/fieldservice_google_map/i18n/fieldservice_google_map.pot
odoo/addons/fieldservice_google_map/i18n/pt_BR.po
odoo/addons/fieldservice_google_map/models/__init__.py
odoo/addons/fieldservice_google_map/models/fsm_location.py
odoo/addons/fieldservice_google_map/models/fsm_order.py
odoo/addons/fieldservice_google_map/readme/CONFIGURE.rst
odoo/addons/fieldservice_google_map/readme/CONTRIBUTORS.rst
odoo/addons/fieldservice_google_map/readme/CREDITS.rst
odoo/addons/fieldservice_google_map/readme/DESCRIPTION.rst
odoo/addons/fieldservice_google_map/readme/INSTALL.rst
odoo/addons/fieldservice_google_map/readme/USAGE.rst
odoo/addons/fieldservice_google_map/static/description/icon.png
odoo/addons/fieldservice_google_map/static/description/index.html
odoo/addons/fieldservice_google_map/views/fsm_location.xml
odoo/addons/fieldservice_google_map/views/fsm_order.xml
odoo14_addon_fieldservice_google_map-14.0.1.1.0.dist-info/METADATA
odoo14_addon_fieldservice_google_map-14.0.1.1.0.dist-info/WHEEL
odoo14_addon_fieldservice_google_map-14.0.1.1.0.dist-info/top_level.txt
odoo14_addon_fieldservice_google_map-14.0.1.1.0.dist-info/RECORD
